ammonite/Object2D.py
ammonite/Object3D.py
ammonite/__init__.py
ammonite-0.1.0.dist-info/LICENSE
ammonite-0.1.0.dist-info/WHEEL
ammonite-0.1.0.dist-info/METADATA
ammonite-0.1.0.dist-info/RECORD
