Metadata-Version: 2.1
Name: ammonite
Version: 0.1.0
Summary: Unit aware calculation of geometrical primitives' area, volumes, etc.
License: GPLv3
Author: Lynda Metref
Author-email: lynda.metref@gmail.com
Requires-Python: >=3.9,<4.0
Classifier: License :: Other/Proprietary License
Classifier: Programming Language :: Python :: 3
Classifier: Programming Language :: Python :: 3.10
Classifier: Programming Language :: Python :: 3.9
Provides-Extra: docs
Requires-Dist: Pint (>=0.18,<0.19)
